README.md
setup.cfg
setup.py
wagtail_tinify/__init__.py
wagtail_tinify/models.py
wagtail_tinify/views.py
wagtail_tinify.egg-info/PKG-INFO
wagtail_tinify.egg-info/SOURCES.txt
wagtail_tinify.egg-info/dependency_links.txt
wagtail_tinify.egg-info/requires.txt
wagtail_tinify.egg-info/top_level.txt
wagtail_tinify/migrations/0001_initial.py
wagtail_tinify/migrations/__init__.py